[
{"Org 2":"Aariha Consultant","Org 9":"AWL Agri Business Limited","Module":"Organisation Name","Org 10":"BECIS","Org 4":"Achyut Realty","Org 5":"Adarsh Developers","Org 8":"Aryaanya Group","Org 7":"Amrut Infracon","Org 3":"Aaryavart Infrastructure Pvt. Ltd.","Org 6":"Amba Township Pvt. Ltd.","Org 1":"."},
{"Org 2":"100% ⬇️","Org 9":"N/A","Module":"Instruction","Org 10":"100% ⬇️","Org 4":"N/A","Org 5":"82% ⬇️","Org 8":"81% ⬇️","Org 7":"N/A","Org 3":"N/A","Org 6":"N/A","Org 1":"142% ⬆️"},
{"Org 2":"75% ⬇️","Org 9":"36% ⬇️","Module":"Inspection","Org 10":"419% ⬆️","Org 4":"N/A","Org 5":"48% ⬇️","Org 8":"61% ⬇️","Org 7":"100% ⬇️","Org 3":"100% ⬇️","Org 6":"3% ⬇️","Org 1":"10% ⬆️"},
{"Org 2":"N/A","Org 9":"N/A","Module":"Register","Org 10":"N/A","Org 4":"N/A","Org 5":"N/A","Org 8":"N/A","Org 7":"N/A","Org 3":"N/A","Org 6":"700% ⬆️","Org 1":"N/A"},
{"Org 2":"Ninad Shah , digiQC Support - Aariha Consultant","Org 9":"digiQC Support - AWL , Kashyap Baxi","Module":"Name","Org 10":"Vipul Patel , Supportdigiqc , Emerson Ongcal , Vasudev Acharya , Nattapol Niyompong","Org 4":"Praveen Kothari , Abhimanyu Khetawat , Support","Org 5":"Support , Chitty Babu , Srinivasa Murthy , Govindaraju A S","Org 8":"Yogesh Suthar , Nidhi Dave , Arpanbhai Raval. , Lavkit jagdishbhai suthar , Rinku , JIGNESH SEVARA , digiQC Support - Aryaanya Group , Kiritbhai Patel , Aviroop , Yogesh Suthar.","Org 7":"digiQC Support , Shoaib Khan , Sanjay Desai , Rutvik Patel","Org 3":"Jigar Patel , Deep , digiQC Support , digiQC Support -  Harsha","Org 6":"Harsha - Vitrag , Nayan Gupta , digiQC Support , Ashish digiQC Support , Dhaval Patel , Vineet Prajapati , Vineet Prajapati","Org 1":"Arindam Pal , Jithesh Babu , Ashish Maheshwari System Admin , Amit Sharma , Myil , digiQC Support - Schueco , Manjunath Marappa , Vaibhav Raje , Tushar Gadkari , Aswath"},
{"Org 2":"+919725309669","Org 9":"+915588994466 , +917203036621","Module":"Phone","Org 10":"+919665745753 , +914565852565 , +639171078897 , +919769329745 , +66880080103","Org 4":"+918102396073 , +919706060818 , +911435768978","Org 5":"+91123232145 , +919880889986 , +919606976115 , +919663713077","Org 8":"9428362179 , +919328284828 , +917383571057 , 7600737813 , +917984935488 , +918128425795 , +919073598010","Org 7":"+919549869993 , +917486050552 , +919662343508","Org 3":"+919316481785","Org 6":"+919574009490 , +919574008091","Org 1":"9051618823 , 8553851995 , +919311123357 , +919036306406 , +918087736163 , +918378880004 , +917624986879"}
]